{
  "kind": "singleType",
  "collectionName": "accounts",
  "info": {
    "singularName": "account",
    "pluralName": "accounts",
    "displayName": "Accounts",
    "description": ""
  },
  "options": {
    "draftAndPublish": true
  },
  "pluginOptions": {
    "i18n": {
      "localized": true
    }
  },
  "attributes": {
    "Slider": {
      "type": "component",
      "repeatable": true,
      "pluginOptions": {
        "i18n": {
          "localized": true
        }
      },
      "component": "page.slideshow"
    },
    "FixedQuickLinks": {
      "type": "component",
      "repeatable": true,
      "pluginOptions": {
        "i18n": {
          "localized": true
        }
      },
      "component": "page.home-quick-links"
    },
    "BankDetails": {
      "displayName": "Bank Details 1",
      "type": "component",
      "repeatable": true,
      "pluginOptions": {
        "i18n": {
          "localized": true
        }
      },
      "component": "page.bank-details-1"
    }
  }
}
